colorize_calls.py
williballenthin_colorize_calls_ida_plugin-0.1.0.dist-info/METADATA
williballenthin_colorize_calls_ida_plugin-0.1.0.dist-info/WHEEL
williballenthin_colorize_calls_ida_plugin-0.1.0.dist-info/entry_points.txt
williballenthin_colorize_calls_ida_plugin-0.1.0.dist-info/top_level.txt
williballenthin_colorize_calls_ida_plugin-0.1.0.dist-info/RECORD
