Metadata-Version: 2.4
Name: williballenthin-colorize-calls-ida-plugin
Version: 0.1.0
Summary: IDA Pro plugin to colorize call instructions and add a prefix
Author-email: Willi Ballenthin <willi.ballenthin@gmail.com>
License-Expression: Apache-2.0
Requires-Python: >=3.9
